resize.py
resize-0.1.0.dist-info/LICENSE
resize-0.1.0.dist-info/METADATA
resize-0.1.0.dist-info/WHEEL
resize-0.1.0.dist-info/entry_points.txt
resize-0.1.0.dist-info/top_level.txt
resize-0.1.0.dist-info/RECORD
