Metadata-Version: 2.1
Name: resize
Version: 0.1.0
Summary: Mass picture resizer.
Home-page: https://github.com/bdabrowski/resizer
Author: Bartosz Dąbrowski
Author-email: bar.dabrowski@gmail.com
License: Copyright 2018 Bartosz Dąbrowski
Requires-Dist: docopt
Requires-Dist: Pillow (==5.3.0)
Provides-Extra: test
Requires-Dist: pytest ; extra == 'test'
Requires-Dist: pytest-datafiles ; extra == 'test'
Requires-Dist: invoke (==0.14.0) ; extra == 'test'
